gradle.properties
hexdoc_hexxyplanes/__gradle_version__.py
hexdoc_hexxyplanes/__init__.py
hexdoc_hexxyplanes/__version__.py
hexdoc_hexxyplanes/_hooks.py
hexdoc_hexxyplanes/py.typed
hexdoc_hexxyplanes/_export/.gitignore
hexdoc_hexxyplanes/_export/__init__.py
hexdoc_hexxyplanes/_export/generated/__init__.py
hexdoc_hexxyplanes/_export/generated/hexxyplanes.hexdoc.json
hexdoc_hexxyplanes/_export/generated/hexxyplanes.patterns.hexdoc.json
hexdoc_hexxyplanes/_export/generated/assets/hexcasting/patchouli_books/thehexbook/en_us/entries/patterns/spells/hexplane.json5
hexdoc_hexxyplanes/_export/generated/assets/hexcasting/patchouli_books/thehexbook/en_us/entries/patterns/spells/oneironaut.json5
hexdoc_hexxyplanes/_export/generated/assets/hexxyplanes/lang/en_us.flatten.json5
"hexdoc_hexxyplanes/_export/generated/assets/hexxyplanes/lang/zh_cn,flatten.json5"
hexdoc_hexxyplanes/_export/generated/assets/hexxyplanes/lang/zh_cn.flatten.json5
hexdoc_hexxyplanes/_export/generated/assets/hexxyplanes/models/block/barrier_model.json
hexdoc_hexxyplanes/_export/generated/assets/hexxyplanes/models/block/barrier_spawn_model.json
hexdoc_hexxyplanes/_export/generated/assets/hexxyplanes/models/item/barrier.json
hexdoc_hexxyplanes/_export/generated/assets/hexxyplanes/models/item/barrier_spawn.json
hexdoc_hexxyplanes/_export/generated/assets/hexxyplanes/textures/block/barrier.png
hexdoc_hexxyplanes/_export/generated/assets/hexxyplanes/textures/block/barrier_spawn.png
hexdoc_hexxyplanes/_export/generated/data/hexcasting/tags/action/per_world_pattern.json
hexdoc_hexxyplanes/_templates/__init__.py
hexdoc_hexxyplanes-0.2.1.1.20.1.1.0.dist-info/METADATA
hexdoc_hexxyplanes-0.2.1.1.20.1.1.0.dist-info/WHEEL
hexdoc_hexxyplanes-0.2.1.1.20.1.1.0.dist-info/entry_points.txt
hexdoc_hexxyplanes-0.2.1.1.20.1.1.0.dist-info/licenses/LICENSE
hexdoc_hexxyplanes-0.2.1.1.20.1.1.0.dist-info/RECORD
