Metadata-Version: 2.4
Name: hexdoc-hexxyplanes
Version: 0.2.1.1.20.1.1.0
Summary: A small personal dimension, perfect for all your secret keeping needs
Project-URL: Homepage, https://real-septicake.github.io/HexxyPlanes
Project-URL: Source, https://github.com/Real-Septicake/HexxyPlanes
Author: Real-Septicake
License-File: LICENSE
Keywords: hexdoc
Requires-Python: >=3.12
Requires-Dist: hexdoc-hexcasting~=0.11.2.1.0
